tc_mailmanager/__init__.py
tc_mailmanager/mail_manager.py
tc_mailmanager/py.typed
tc_mailmanager-1.7.1.dist-info/WHEEL
tc_mailmanager-1.7.1.dist-info/METADATA
tc_mailmanager-1.7.1.dist-info/RECORD
