Metadata-Version: 2.1
Name: tc-mailmanager
Version: 1.7.1
Summary: ToucanToco's cross-python-projects MailManager
Home-page: https://github.com/ToucanToco/tc_mailmanager
License: BSD-3-Clause
Author: Toucan Toco
Author-email: dev@toucantoco.com
Requires-Python: >=3.8,<4.0
Classifier: Intended Audience :: Developers
Classifier: License :: OSI Approved :: BSD License
Classifier: Programming Language :: Python :: 3
Classifier: Programming Language :: Python :: 3.8
Classifier: Programming Language :: Python :: 3.9
Classifier: Programming Language :: Python :: 3.10
Classifier: Programming Language :: Python :: 3.11
Classifier: Programming Language :: Python :: 3 :: Only
Classifier: Programming Language :: Python :: 3.10
Classifier: Programming Language :: Python :: 3.8
Classifier: Programming Language :: Python :: 3.9
Classifier: Typing :: Typed
Requires-Dist: sendgrid (>=5,<6)
Requires-Dist: tctc-envelopes (==0.5)
Project-URL: Documentation, https://toucantoco.github.io/tc_mailmanager
Project-URL: Repository, https://github.com/ToucanToco/tc_mailmanager
